mcp_excel_server/__init__.py
mcp_excel_server/server.py
mcp_excel_server-1.0.4.dist-info/METADATA
mcp_excel_server-1.0.4.dist-info/WHEEL
mcp_excel_server-1.0.4.dist-info/entry_points.txt
mcp_excel_server-1.0.4.dist-info/top_level.txt
mcp_excel_server-1.0.4.dist-info/RECORD
