Metadata-Version: 2.4
Name: mcp-excel-server
Version: 1.0.4
Summary: MCP Excel Server for Excel operations through the Model Context Protocol
Author-email: yzfly <ethereal_ai@hotmail.com>
License: MIT
Project-URL: Homepage, https://github.com/yzfly/mcp-excel-server
Project-URL: Documentation, https://github.com/yzfly/mcp-excel-server/blob/main/README.md
Project-URL: Repository, https://github.com/yzfly/mcp-excel-server.git
Project-URL: Issues, https://github.com/yzfly/mcp-excel-server/issues
Requires-Python: >=3.10
Requires-Dist: mcp[cli]>=1.2.0
Requires-Dist: pandas>=1.3.0
Requires-Dist: numpy>=1.20.0
Requires-Dist: matplotlib>=3.4.0
Requires-Dist: seaborn>=0.11.0
Requires-Dist: openpyxl>=3.0.0
Requires-Dist: build>=1.2.2.post1
Requires-Dist: twine>=6.1.0
Provides-Extra: dev
Requires-Dist: pytest>=7.0.0; extra == "dev"
Requires-Dist: black>=23.0.0; extra == "dev"
Requires-Dist: isort>=5.0.0; extra == "dev"
Requires-Dist: flake8>=6.0.0; extra == "dev"
